qatools/__init__.py
qatools/cli.py
qatools/qa.py
qatools/qatools.qa
qatools/adb/mac/adb
qatools/adb/windows/AdbWinApi.dll
qatools/adb/windows/AdbWinUsbApi.dll
qatools/adb/windows/adb.exe
qatools-0.1.3.dist-info/LICENSE
qatools-0.1.3.dist-info/METADATA
qatools-0.1.3.dist-info/WHEEL
qatools-0.1.3.dist-info/entry_points.txt
qatools-0.1.3.dist-info/top_level.txt
qatools-0.1.3.dist-info/RECORD
