Metadata-Version: 2.1
Name: qatools
Version: 0.1.3
Summary: QA is an advanced tool for Android testing!
Home-page: https://openutx.cn/
Author: lijiawei
Author-email: jiawei.li2@qq.com
License: Apache License 2.0
Keywords: utx,adb,qa,tools
Platform: any
Classifier: Development Status :: 5 - Production/Stable
Classifier: Environment :: Console :: Curses
Classifier: Operating System :: MacOS
Classifier: Operating System :: Microsoft :: Windows
Classifier: Programming Language :: Python :: 3 :: Only
Classifier: Programming Language :: Python :: 3.6
Classifier: Programming Language :: Python :: 3.7
Classifier: Programming Language :: Python :: 3.8
Classifier: Programming Language :: Python :: 3.9
Classifier: Programming Language :: Python :: 3.10
Classifier: Programming Language :: Python :: 3.11
Classifier: Programming Language :: Python :: Implementation :: CPython
License-File: LICENSE
Requires-Dist: psutil
